Workbook

Sheet Start Here
A1: PakFreight Star Builder — Week 3 Activity
A2: Data Warehousing & Business Intelligence · Week 3 — Fact & Dimension Tables · CLO2 · The Superior University, Lahore
A4: THE SITUATION
A5: Week 2 ended with one flat table: Shipments_Unified, 34 rows, 578,650 kg, PKR 4,808,000. It answers simple questions and fails at every interesting one — there is no province column, no month column, Karachi is spelled five different ways, and nothing in it remembers what a route used to be called. Today you split it into one fact table and five dimensions, and the totals must not move by a single kilogram.
A7: HOW TO WORK
A8: • Teams of 3. Name one person each: Modeller (owns the grain), Conformer (owns DimCity), Reconciler (owns T7 and has veto power over 'it looks fine').
A9: • Do the tasks in order. T6 cannot be filled in before T4 and T5 exist — that is not a quirk of this workbook, it is why dimensions are always loaded before facts.
A10: • Type only in CREAM cells. GREY cells are source data as received — never edit them.
A11: • T7 marks itself. Every '✘ fix' means something earlier is still wrong. Do not submit with a red cell and a hopeful note.
A12: • Save as W3_Star_<team number>.xlsx and submit on the LMS before Week 4, with the Power BI file described in PakFreight_W3_PowerBI_Lab_Guide.md.
A14: THE SEVEN TASKS
A15: # | B15: Task | C15: What you produce | D15: 180-min class | E15: 120-min class | F15: Where it comes from in the lecture
A16: T1 | B16: Classify every column | C16: Fact, dimension attribute, degenerate or drop | D16: 10 | E16: 8 | F16: Slides 9-17 · what belongs where
A17: T2 | B17: Declare the grain | C17: One sentence, no 'and' — for PakFreight and 4 new processes | D17: 12 | E17: 10 | F17: Slides 19-24 · Kimball's four steps
A18: T3 | B18: Additivity audit | C18: Additive, semi-additive, non-additive — and prove the ratio trap | D18: 10 | E18: 7 | F18: Slide 10 · 8.06 vs 8.31
A19: T4 | B19: Build DimCity | C19: Conform 23 raw location strings into 14 cities, mint the keys | D19: 20 | E19: 15 | F19: Slides 11, 30, 43 · surrogate keys
A20: T5 | B20: Build the other four dimensions | C20: DimRoute, DimMode, DimStatus, DimDate | D20: 20 | E20: 15 | F20: Slides 31-34, 38, 44
A21: T6 | B21: Build FactShipment | C21: Swap every text column for an integer key | D21: 15 | E21: 12 | F21: Slides 9, 44 · merge on the key only
A22: T7 | B22: Reconcile | C22: Thirteen checks. All thirteen must read 'pass' | D22: 8 | E22: 8 | F22: Slide 46 · validate before you trust
C23: Total minutes | D23: 95 | E23: 75
A25: COLOUR LEGEND
B26: You type here
B27: Source data — do not edit
B28: ✔ pass — check satisfied
B29: ✘ fix — go back and correct it
B30: Model answer (teacher key only)
A32: THE GRAIN CONTRACT — WRITE IT ONCE, OBEY IT EVERYWHERE
B33: Decision | C33: Your answer (T2 fills this in) | F33: Why it matters
B34: Business process | C34: Freight shipment movement | F34: Step 1 of Kimball's four steps — pick a process, not a department.
B35: Grain (one row = ?) | F35: Step 2. If your sentence needs the word 'and', you have two fact tables.
B36: Fact table type | F36: Transaction, periodic snapshot or accumulating snapshot.
B37: Dimensions | F37: Step 3 — and they must follow from the grain, not from your imagination.
B38: Measures | F38: Step 4 — additive wherever you can manage it.

Sheet Shipments_Unified
A1: Shipments_Unified — the Week 2 output
A2: 34 rows · 578,650 kg · PKR 4,808,000. Grey means source data: read it, point formulas at it, never edit it. This whole sheet becomes FactShipment in T6.
A4: ShipmentID | B4: ShipDate | C4: Origin | D4: Destination | E4: WeightKG | F4: CostPKR | G4: Status | H4: SourceSystem
A5: MR-1001 | B5: 46054 | C5: Karachi Port | D5: Lahore Dry Port | E5: 18000 | F5: 142000 | G5: Delivered | H5: Marine
A6: MR-1002 | B6: 46055 | C6: Port Qasim | D6: Faisalabad Dry Port | E6: 22500 | F6: 171000 | G6: Delivered | H6: Marine
A7: MR-1003 | B7: 46056 | C7: Karachi Port | D7: Lahore Dry Port | E7: 15000 | F7: 119000 | G7: In Transit | H7: Marine
A8: MR-1004 | B8: 46057 | C8: Gwadar Port | D8: Quetta | E8: 20000 | F8: 188000 | G8: Delivered | H8: Marine
A9: MR-1005 | B9: 46058 | C9: Port Qasim | D9: Multan | E9: 16500 | F9: 128000 | G9: Delivered | H9: Marine
A10: MR-1006 | B10: 46059 | C10: Karachi Port | D10: Sialkot Dry Port | E10: 19000 | F10: 154000 | G10: Delayed | H10: Marine
A11: MR-1007 | B11: 46060 | C11: Port Qasim | D11: Lahore Dry Port | E11: 14000 | F11: 109000 | G11: Delivered | H11: Marine
A12: MR-1008 | B12: 46062 | C12: Karachi Port | D12: Peshawar | E12: 21000 | F12: 197000 | G12: In Transit | H12: Marine
A13: MR-1009 | B13: 46063 | C13: Gwadar Port | D13: Karachi Cantt | E13: 17500 | F13: 98000 | G13: Delivered | H13: Marine
A14: MR-1010 | B14: 46064 | C14: Port Qasim | D14: Islamabad Dry Port | E14: 15500 | F14: 139000 | G14: Delivered | H14: Marine
A15: MR-1011 | B15: 46065 | C15: Karachi Port | D15: Hyderabad | E15: 13500 | F15: 61000 | G15: In Transit | H15: Marine
A16: MR-1012 | B16: 46066 | C16: Port Qasim | D16: Lahore Dry Port | E16: 14000 | F16: 112000 | G16: Delivered | H16: Marine
... A38: RD-512 | B38: 46066 | C38: Rawalpindi | D38: Abbottabad | E38: 5800 | F38: 45000 | G38: Delivered | H38: Road
D39: TOTAL | E39: =SUM(E5:E38) | F39: =SUM(F5:F38)
A41: Count the distinct dates in column B. There are 12 — not 28. February 2026 has 28 days and PakFreight dispatched nothing on 16 of them. Any 'average per day' computed from this sheet divides by the wrong number, silently. That is what DimDate in T5 is for.

Sheet T1 Classify
A1: T1 · Fact, Dimension, Degenerate or Drop?
A2: PakFreight's operations team wants twelve more columns added to the warehouse. For each one write F (fact / measure), D (dimension attribute), DD (degenerate dimension) or X (belongs in neither), name the table it should live in, and defend it in one line. Four of the twelve are deliberately tricky.
A4: # | B4: Column the team asked for | C4: F / D / DD / X | D4: Which table does it live in? | E4: Your one-line justification
A5: 1 | B5: Driver_Name | C5: D | D5: DimDriver | E5: Driver identity describes the person; keep descriptive driver attributes in a driver dimension.
A6: 2 | B6: Days_Late | C6: F | D6: FactShipment | E6: Delay days are a numeric outcome measured at the shipment-leg grain.
A7: 3 | B7: Invoice_Number | C7: DD | D7: FactShipment | E7: Invoice number identifies the transaction but has no independent descriptive attributes.
A8: 4 | B8: Discount_Percent | C8: F | D8: FactShipment | E8: A percentage is non-additive; retain discount amount and eligible base amount, then divide.
A9: 5 | B9: Truck_Registration_No | C9: D | D9: DimVehicle | E9: Registration identifies a vehicle with descriptive attributes, so it merits a vehicle dimension.
A10: 6 | B10: Container_Count | C10: F | D10: FactShipment | E10: Container count is an additive quantity at the shipment-leg grain.
A11: 7 | B11: Customer_Credit_Rating | C11: D | D11: DimCustomer | E11: Credit rating describes a customer; use history (such as Type 2) when ratings change.
A12: 8 | B12: Cost_Per_Tonne_KM | C12: F | D12: FactShipment | E12: Cost per tonne-km is a derived ratio; store cost, tonnes and distance, then calculate.
A13: 9 | B13: Row_Inserted_Timestamp | C13: X | D13: ETL audit metadata | E13: Load timestamp supports lineage and operations, not the business dimensional model.
A14: 10 | B14: Fuel_Surcharge_PKR | C14: F | D14: FactShipment | E14: Fuel surcharge is a monetary component that can be summed across shipment legs.
A15: 11 | B15: Weather_Condition | C15: D | D15: DimWeather | E15: Weather condition is descriptive context for the shipment event.
A16: 12 | B16: Is_Hazardous_Cargo | C16: D | D16: DimCargo / DimHazard | E16: Hazard flag describes cargo; model it as a cargo/hazard attribute or small junk dimension.
B17: Answered so far | C17: =COUNTA(C5:C16)&" / 12"
A19: DEFEND YOUR ANSWERS — THE THREE QUESTIONS WE WILL ASK
A20: Which of your X answers would a real analyst fight you over, and what is their best argument? | C20: Row_Inserted_Timestamp is the debatable X: an analyst can argue it is useful for lineage, but it belongs in ETL audit metadata, not a business dimension or measure.
A22: Name one column you marked D that deserves its own dimension table, and three attributes it would carry. | C22: Driver_Name merits DimDriver; useful attributes include licence class, home depot and employment/qualification status.
A24: If Days_Late is a fact, which dimension supplies the deadline it is measured against? | C24: The due-date role of DimDate supplies the deadline; compare it with the actual delivery date role to calculate Days_Late.
A27: Marking: 6 marks for the twelve verdicts (half a mark each), 3 marks for the justifications, 3 marks for the three questions. A wrong verdict with a sharp justification scores more than a right verdict with none — the reasoning is the skill.

Sheet T2 Grain
A1: T2 · Declare the Grain
A2: The single most consequential sentence in warehouse design. Write it for PakFreight, then for four processes PakFreight wants to add next. Use the template: 'One row per …'. If your sentence needs the word 'and', you have described two fact tables.
A4: PART A · THE PAKFREIGHT GRAIN STATEMENT
B5: One row of FactShipment represents… | C5: One row per shipment leg dispatched by PakFreight. | F5: =IF(C5="","— not written yet",IF(ISNUMBER(SEARCH(" and ",C5)),"✘ contains 'and' — that is two fact tables","✔ no 'and' — one grain"))
A6: Why 'leg' and not 'shipment'? MR-1009 moves Gwadar → Karachi and RD-508 moves Quetta → Karachi. If a single customer consignment is later carried marine-then-road, 'one row per shipment' becomes ambiguous the day PakFreight sells multi-modal freight — and the grain you declare today is the one the CFO's 2027 reports will be built on.
A8: PART B · FOUR NEW PROCESSES — GRAIN, DIMENSIONS, MEASURES, FACT TYPE
A9: # | B9: Business process | C9: Grain sentence (one row per …) | D9: Dimensions it implies | E9: Two measures | F9: Fact table type + why
A10: 1 | B10: Fuel purchases at PakFreight depots | C10: fuel purchase transaction line | D10: Date, Depot/Location, Supplier, FuelType, Vehicle | E10: Litres purchased; PurchaseCostPKR | F10: Transaction: one row records a completed purchase line.
B11: Hint: Is the grain one fuel purchase, one litre, or one truck per week?
A12: 2 | B12: Driver duty hours and rest compliance | C12: driver shift worked by one driver on one date | D12: Date, Driver, Depot | E12: DutyHours; RestHours | F12: Transaction: keep one row per shift; calculate rolling 14-day compliance from shift measures.
B13: Hint: Regulators care about a rolling 14-day window. Does that change the grain, or only the measures?
A14: 3 | B14: Customer complaints about late delivery | C14: customer complaint/ticket from opening through resolution | D14: Customer, ComplaintType, Status, CreatedDate, ResolvedDate | E14: ResolutionDays; ComplaintCount | F14: Accumulating snapshot: update milestone dates/status as the ticket progresses; use a ComplaintShipment bridge for multiple shipments.
B15: Hint: One complaint can reference several shipments. Where does that relationship live?
A16: 4 | B16: Daily warehouse stock levels at Lahore Dry Port | C16: product at Lahore Dry Port at the close of each calendar day | D16: Date, Product, Warehouse/Depot | E16: OnHandUnits; StockValuePKR | F16: Periodic snapshot: record balances each day, including quiet days.
B17: Hint: Nothing 'happens' on a quiet day — but you still need a number. Which fact shape is this?
A19: PART C · THE GRAIN THAT WENT WRONG — A 20-SECOND CASE
B20: A PakFreight analyst needs cost per customer, so he adds CustomerName to FactShipment. Two shipments on RD-501 are billed to two customers who split the truck. He cannot choose, so he duplicates the row — once per customer. The table now has 35 rows, total weight reads 585,150 kg, and every weight report in the company is overstated by 6,500 kg forever. In one line each: (a) what rule did he break? (b) what should he have built instead? (c) which of T7's twelve checks would have caught it?
B23: Adding CustomerName broke the declared one-row-per-shipment-leg grain and duplicated shipment measures. Keep FactShipment at leg grain; use a ShipmentCustomer allocation bridge/fact with agreed allocation percentages and allocated weight/cost. T7 checks #1 (row count), #2 (weight), #3 (cost) and #4 (shipment count) would expose duplication; #5 distinct IDs alone may not.
A26: Marking, 12 marks: Part A grain sentence 3 · Part B 1.5 per process (grain 0.75, dimensions 0.5, measures 0.25) · Part C 3 · bonus 1 for spotting that #4 is a periodic snapshot and #3 needs a bridge table. A sentence containing 'and' loses the grain mark however good the rest is.

Sheet T3 Additivity
A1: T3 · Additivity Audit — and the ratio that lies by 3%
A2: A measure is only useful once you know which dimensions you may add it across. Classify ten measures, then prove the ratio trap on PakFreight's own 34 rows.
A4: # | B4: Candidate measure | C4: Additive / Semi / Non | D4: Safe to SUM across time? | E4: What should you store instead? | F4: Notes / your reasoning
A5: 1 | B5: WeightKG | C5: Additive | D5: Yes | E5: Store kilograms at leg grain; sum across dates and other dimensions. | F5: Classification is at the declared grain; ratios and snapshots need the stated aggregation rule.
A6: 2 | B6: FreightCostPKR | C6: Additive | D6: Yes | E6: Store PKR cost components; sum across dates and dimensions. | F6: Classification is at the declared grain; ratios and snapshots need the stated aggregation rule.
A7: 3 | B7: ShipmentCount (=1) | C7: Additive | D7: Yes | E7: Store 1 per leg; sum to count legs. | F7: Classification is at the declared grain; ratios and snapshots need the stated aggregation rule.
A8: 4 | B8: TrucksAvailable at a depot | C8: Semi-additive | D8: No | E8: Store the depot-level snapshot; sum across depots, select a point/period-end across time. | F8: Classification is at the declared grain; ratios and snapshots need the stated aggregation rule.
A9: 5 | B9: WarehouseStockKG | C9: Semi-additive | D9: No | E9: Store daily stock balance; sum across products/depots as appropriate, not across days. | F9: Classification is at the declared grain; ratios and snapshots need the stated aggregation rule.
A10: 6 | B10: CostPerKG | C10: Non-additive | D10: No | E10: Store FreightCostPKR and WeightKG; calculate total cost divided by total weight. | F10: Classification is at the declared grain; ratios and snapshots need the stated aggregation rule.
A11: 7 | B11: OnTimePercent | C11: Non-additive | D11: No | E11: Store on-time count and eligible shipment count; divide after aggregation. | F11: Classification is at the declared grain; ratios and snapshots need the stated aggregation rule.
A12: 8 | B12: TruckUtilisationRate | C12: Non-additive | D12: No | E12: Store occupied hours and available hours; calculate the ratio after aggregation. | F12: Classification is at the declared grain; ratios and snapshots need the stated aggregation rule.
A13: 9 | B13: Days_Late | C13: Additive | D13: Yes | E13: Store delay days per leg; sum for total delay-days (use averages for typical delay). | F13: Classification is at the declared grain; ratios and snapshots need the stated aggregation rule.
A14: 10 | B14: AverageWeightPerShipment | C14: Non-additive | D14: No | E14: Store WeightKG and ShipmentCount; calculate their ratio. Do not average stored averages. | F14: Classification is at the declared grain; ratios and snapshots need the stated aggregation rule.
A16: THE PROOF · AVERAGE OF A RATIO vs RATIO OF TWO SUMS — SAME 34 ROWS, TWO DIFFERENT ANSWERS
B17: WRONG — average the per-row ratio | C17: =SUMPRODUCT(Shipments_Unified!F5:F38/Shipments_Unified!E5:E38)/34 | D17: What AVERAGE(Cost/Weight) gives you, and what a careless DAX measure gives you.
B18: RIGHT — divide the two sums | C18: =SUM(Shipments_Unified!F5:F38)/SUM(Shipments_Unified!E5:E38) | D18: What DIVIDE(SUM(Cost), SUM(Weight)) gives you. The only version that is correct at every level.
B19: The gap, in PKR per kg | C19: =C18-C17 | D19: Small enough that nobody notices. On PakFreight's real annual volume it is tens of millions.
B20: The gap, as a percentage | C20: =(C18-C17)/C17 | D20: No error is raised. No cell turns red. The number is simply wrong.
B21: Expected: 8.0604 (wrong) and 8.3090 (right)
A23: ANSWER IN ONE LINE EACH
B24: Which of the two numbers above would you put on a board slide, and what exactly does the other one measure? | D24: Put 8.3090 PKR/kg on the board slide: total freight cost divided by total kg. 8.0604 is the unweighted mean of 34 shipment-level cost/kg ratios; it answers the cost/kg for an average leg, giving a small leg the same weight as a large one.
B26: For each province, divide SUM(FreightCostPKR) by SUM(WeightKG) for legs originating there. Aggregate the two additive components first, then divide; never average shipment-level cost/kg ratios.
B28: Name the one measure in the table above whose correct answer is 'delete the column', and say why a stored average can never be fixed later. | D28: AverageWeightPerShipment: delete the stored average column because WeightKG and ShipmentCount already retain its full numerator and denominator. A stored average has discarded the underlying weighting and cannot be correctly rolled up from averages alone.
A31: Marking, 10 marks: classification 5 (half a mark per row) · 'store instead' column 2 · the three questions 3. Full marks on question 1 require naming what 8.06 actually measures — 'it is wrong' is not an answer.

Sheet T4 DimCity
A1: T4 · Conform 23 Location Strings into 14 Cities
A2: This is the editorial act of dimensional modelling, and it is yours. Block 1: decide what each raw string really is. Block 2: build the dimension, one row per real-world city, with a surrogate key you mint yourself.
A4: BLOCK 1 · THE CONFORMING MAP — 23 RAW STRINGS, EXACTLY AS THE SOURCE SYSTEMS WROTE THEM
A5: # | B5: Raw location string (grey — do not edit) | C5: Conformed CityName | D5: Province | E5: Region | F5: Port city? | G5: Facility type | I5: CityKey | J5: CityName | K5: Province | L5: Region | M5: Port? | N5: FacilityType | O5: SourceAliases (which raw strings map here)
A6: 1 | B6: Karachi Port | C6: Karachi | D6: Sindh | E6: South | F6: Yes | G6: Port / rail hub | I6: 1 | J6: Karachi | K6: Sindh | L6: South | M6: Yes | N6: Port / rail hub | O6: =IF($J6="","",TEXTJOIN(" | ",TRUE,IF($C$6:$C$28=$J6,$B$6:$B$28,"")))
A7: 2 | B7: Port Qasim | C7: Karachi | D7: Sindh | E7: South | F7: Yes | G7: Port / rail hub | I7: 2 | J7: Gwadar | K7: Balochistan | L7: South | M7: Yes | N7: Sea port | O7: =IF($J7="","",TEXTJOIN(" | ",TRUE,IF($C$6:$C$28=$J7,$B$6:$B$28,"")))
A8: 3 | B8: Gwadar Port | C8: Gwadar | D8: Balochistan | E8: South | F8: Yes | G8: Sea port | I8: 3 | J8: Lahore | K8: Punjab | L8: North | M8: No | N8: Dry port / rail hub | O8: =IF($J8="","",TEXTJOIN(" | ",TRUE,IF($C$6:$C$28=$J8,$B$6:$B$28,"")))
A9: 4 | B9: Karachi Cantt | C9: Karachi | D9: Sindh | E9: South | F9: Yes | G9: Port / rail hub | I9: 4 | J9: Multan | K9: Punjab | L9: Central | M9: No | N9: Inland depot | O9: =IF($J9="","",TEXTJOIN(" | ",TRUE,IF($C$6:$C$28=$J9,$B$6:$B$28,"")))
A10: 5 | B10: Pipri Marshalling Yard | C10: Karachi | D10: Sindh | E10: South | F10: Yes | G10: Port / rail hub | I10: 5 | J10: Islamabad | K10: Islamabad ICT | L10: North | M10: No | N10: Dry port | O10: =IF($J10="","",TEXTJOIN(" | ",TRUE,IF($C$6:$C$28=$J10,$B$6:$B$28,"")))
A11: 6 | B11: Lahore | C11: Lahore | D11: Punjab | E11: North | F11: No | G11: Dry port / rail hub | I11: 6 | J11: Quetta | K11: Balochistan | L11: West | M11: No | N11: Inland depot | O11: =IF($J11="","",TEXTJOIN(" | ",TRUE,IF($C$6:$C$28=$J11,$B$6:$B$28,"")))
A12: 7 | B12: Karachi | C12: Karachi | D12: Sindh | E12: South | F12: Yes | G12: Port / rail hub | I12: 7 | J12: Faisalabad | K12: Punjab | L12: Central | M12: No | N12: Dry port | O12: =IF($J12="","",TEXTJOIN(" | ",TRUE,IF($C$6:$C$28=$J12,$B$6:$B$28,"")))
A13: 8 | B13: Multan | C13: Multan | D13: Punjab | E13: Central | F13: No | G13: Inland depot | I13: 8 | J13: Rawalpindi | K13: Punjab | L13: North | M13: No | N13: Rail hub | O13: =IF($J13="","",TEXTJOIN(" | ",TRUE,IF($C$6:$C$28=$J13,$B$6:$B$28,"")))
A14: 9 | B14: Islamabad | C14: Islamabad | D14: Islamabad ICT | E14: North | F14: No | G14: Dry port | I14: 9 | J14: Sialkot | K14: Punjab | L14: North | M14: No | N14: Dry port | O14: =IF($J14="","",TEXTJOIN(" | ",TRUE,IF($C$6:$C$28=$J14,$B$6:$B$28,"")))
A15: 10 | B15: Quetta | C15: Quetta | D15: Balochistan | E15: West | F15: No | G15: Inland depot | I15: 10 | J15: Peshawar | K15: Khyber Pakhtunkhwa | L15: North | M15: No | N15: Inland depot | O15: =IF($J15="","",TEXTJOIN(" | ",TRUE,IF($C$6:$C$28=$J15,$B$6:$B$28,"")))
A16: 11 | B16: Faisalabad | C16: Faisalabad | D16: Punjab | E16: Central | F16: No | G16: Dry port | I16: 11 | J16: Hyderabad | K16: Sindh | L16: South | M16: No | N16: Inland depot | O16: =IF($J16="","",TEXTJOIN(" | ",TRUE,IF($C$6:$C$28=$J16,$B$6:$B$28,"")))
A17: 12 | B17: Rawalpindi | C17: Rawalpindi | D17: Punjab | E17: North | F17: No | G17: Rail hub | I17: 12 | J17: Sukkur | K17: Sindh | L17: Central | M17: No | N17: Inland depot | O17: =IF($J17="","",TEXTJOIN(" | ",TRUE,IF($C$6:$C$28=$J17,$B$6:$B$28,"")))
... A19: 14 | B19: Faisalabad Dry Port | C19: Faisalabad | D19: Punjab | E19: Central | F19: No | G19: Dry port | I19: 14 | J19: Abbottabad | K19: Khyber Pakhtunkhwa | L19: North | M19: No | N19: Inland depot | O19: =IF($J19="","",TEXTJOIN(" | ",TRUE,IF($C$6:$C$28=$J19,$B$6:$B$28,"")))
A20: 15 | B20: Sialkot Dry Port | C20: Sialkot | D20: Punjab | E20: North | F20: No | G20: Dry port | I20: -1 | J20: Unknown | K20: Unknown | L20: Unknown | M20: Unknown | N20: Unknown | O20: Unknown
A21: 16 | B21: Peshawar | C21: Peshawar | D21: Khyber Pakhtunkhwa | E21: North | F21: No | G21: Inland depot
A22: 17 | B22: Islamabad Dry Port | C22: Islamabad | D22: Islamabad ICT | E22: North | F22: No | G22: Dry port
A23: 18 | B23: Hyderabad | C23: Hyderabad | D23: Sindh | E23: South | F23: No | G23: Inland depot
A24: 19 | B24: Peshawar Cantt | C24: Peshawar | D24: Khyber Pakhtunkhwa | E24: North | F24: No | G24: Inland depot
A25: 20 | B25: Sukkur | C25: Sukkur | D25: Sindh | E25: Central | F25: No | G25: Inland depot
A26: 21 | B26: Sialkot | C26: Sialkot | D26: Punjab | E26: North | F26: No | G26: Dry port
A27: 22 | B27: Gujranwala | C27: Gujranwala | D27: Punjab | E27: North | F27: No | G27: Inland depot
A28: 23 | B28: Abbottabad | C28: Abbottabad | D28: Khyber Pakhtunkhwa | E28: North | F28: No | G28: Inland depot
A30: SELF-CHECK · THESE THREE MUST ALL PASS BEFORE YOU START T5
C31: Check | D31: Expected | E31: Your result | F31: Pass?
C32: Distinct conformed city names in Block 1 | D32: 14 | E32: =SUMPRODUCT((C6:C28<>"")/COUNTIF(C6:C28,C6:C28&"")) | F32: =IF(E32=D32,"✔ pass","✘ fix") | G32: If you get 15 or more you have left two spellings of one city apart. If 13 or fewer you have merged two genuinely different cities — check Islamabad against Rawalpindi.
C33: Raw strings that map to Karachi | D33: 5 | E33: =COUNTIF(C6:C28,"Karachi") | F33: =IF(E33=D33,"✔ pass","✘ fix") | G33: Karachi Port, Port Qasim, Karachi Cantt, Pipri Marshalling Yard and plain Karachi are five facilities in one city. Merging them is the whole point; getting 2 means you kept the rail yards separate.
C34: Rows in DimCity, excluding the Unknown row | D34: 14 | E34: =COUNTIF(I6:I20,">0") | F34: =IF(E34=D34,"✔ pass","✘ fix") | G34: Fourteen cities plus one reserved row with key -1. The -1 row is not optional — T6 needs somewhere to point when a future file arrives with a city nobody has mapped.
A36: THE JUDGEMENT CALL — ANSWER BEFORE YOU MOVE ON
B37: Consolidating Pipri with Karachi treats its rail yard as part of the Karachi service market; that can shift port-versus-inland capacity, investment or service-performance decisions.
B39: Mapping Islamabad to Punjab misstates provincial freight, budgets and service comparisons; leaving Province blank drops or misgroups weight in provincial totals. Map it to Islamabad ICT.
B41: Add the new raw label to the conformance map as Karachi (Sindh, South, port city, port facility), refresh the mapping, resolve its CityKey, then load/re-key affected fact rows and rerun the reconciliation checks.
A44: Marking, 20 marks: conforming map 8 · provinces and regions correct 4 · DimCity built with a reused -1 row 4 · the three judgement questions 4. Karachi must be CityKey 1 everywhere it appears for the rest of the workbook to reconcile.

Sheet T5 Other Dimensions
A1: T5 · DimRoute, DimMode, DimStatus, DimDate
A2: Four more dimensions. One of them contains a trap that the lecture slides walk straight past — find it in Block A before you fill anything in.
A4: BLOCK A · DIMROUTE — 20 ROWS. BUT THE RAW DATA HAS 30 DISTINCT PAIRS.
A5: The lab brief says: 'Keep Origin and Destination, Remove Duplicates → 20 rows.' Try it on Shipments_Unified and you get 30. Column I below lists all 30 raw pairs. Before you build anything: write down why the two numbers differ, and which operation has to happen first.
B7: Your answer: | C7: First map each raw Origin and Destination through the 23-to-14 DimCity conformance map, expand the CityKeys/CityNames, then remove duplicates on the pair of conformed CityKeys. Dedupe-before-conformance leaves 30 alias pairs; after conformance there are 20 real origin-destination routes.
A9: # | B9: RouteKey | C9: OriginCityKey | D9: DestCityKey | E9: RouteName | F9: Corridor | G9: DistanceBand | I9: The 30 RAW origin → destination pairs (grey)
A10: 1 | B10: 1 | C10: 1 | D10: 3 | E10: Karachi -> Lahore | F10: South-North trunk | G10: Long (>700 km) | I10: Karachi Port → Lahore Dry Port
A11: 2 | B11: 2 | C11: 1 | D11: 7 | E11: Karachi -> Faisalabad | F11: South-North trunk | G11: Long (>700 km) | I11: Port Qasim → Faisalabad Dry Port
A12: 3 | B12: 3 | C12: 2 | D12: 6 | E12: Gwadar -> Quetta | F12: Balochistan corridor | G12: Long (>700 km) | I12: Gwadar Port → Quetta
A13: 4 | B13: 4 | C13: 1 | D13: 4 | E13: Karachi -> Multan | F13: South-North trunk | G13: Long (>700 km) | I13: Port Qasim → Multan
A14: 5 | B14: 5 | C14: 1 | D14: 9 | E14: Karachi -> Sialkot | F14: South-North trunk | G14: Long (>700 km) | I14: Karachi Port → Sialkot Dry Port
A15: 6 | B15: 6 | C15: 1 | D15: 10 | E15: Karachi -> Peshawar | F15: South-North trunk | G15: Long (>700 km) | I15: Port Qasim → Lahore Dry Port
A16: 7 | B16: 7 | C16: 2 | D16: 1 | E16: Gwadar -> Karachi | F16: Balochistan connector | G16: Medium (301-700 km) | I16: Karachi Port → Peshawar
A17: 8 | B17: 8 | C17: 1 | D17: 5 | E17: Karachi -> Islamabad | F17: South-North trunk | G17: Long (>700 km) | I17: Gwadar Port → Karachi Cantt
A18: 9 | B18: 9 | C18: 1 | D18: 11 | E18: Karachi -> Hyderabad | F18: Sindh corridor | G18: Short (<=300 km) | I18: Port Qasim → Islamabad Dry Port
A19: 10 | B19: 10 | C19: 1 | D19: 8 | E19: Karachi -> Rawalpindi | F19: South-North trunk | G19: Long (>700 km) | I19: Karachi Port → Hyderabad
A20: 11 | B20: 11 | C20: 1 | D20: 12 | E20: Karachi -> Sukkur | F20: Sindh corridor | G20: Medium (301-700 km) | I20: Karachi Cantt → Lahore
A21: 12 | B21: 12 | C21: 3 | D21: 5 | E21: Lahore -> Islamabad | F21: Central-North connector | G21: Short (<=300 km) | I21: Karachi Cantt → Rawalpindi
... A29: 20 | B29: 20 | C29: 8 | D29: 14 | E29: Rawalpindi -> Abbottabad | F29: Central-North connector | G29: Short (<=300 km) | I29: Lahore → Islamabad
B30: -1 | C30: -1 | D30: -1 | E30: Unknown | F30: Unknown | G30: Unknown | I30: Karachi → Hyderabad
I31: Lahore → Faisalabad
I32: Multan → Lahore
I33: Islamabad → Peshawar
I34: Karachi → Sukkur
I35: Lahore → Sialkot
I36: Quetta → Karachi
I37: Faisalabad → Multan
I38: Lahore → Gujranwala
I39: Rawalpindi → Abbottabad
I40: 30 raw pairs → 20 conformed routes
B41: Check · distinct RouteName values | E41: =SUMPRODUCT((E10:E30<>"")/COUNTIF(E10:E30,E10:E30&"")) | F41: 21 | G41: =IF(E41=F41,"✔ pass","✘ fix") | I41: 20 real routes + 1 Unknown row = 21 distinct names.
A43: BLOCK B · DIMMODE AND DIMSTATUS — TYPED BY HAND. THIS IS REFERENCE DATA, NOT SOURCE DATA.
B44: ModeKey | C44: ModeName | D44: Carrier | E44: TonnageClass | F44: CostProfile | G44: Containerised? | K44: StatusKey | L44: StatusName | M44: IsClosed | N44: IsException | O44: DisplayOrder
B45: 1 | C45: Marine | D45: PakFreight Shipping Ltd | E45: Heavy (10-25 t) | F45: Low cost / slow | G45: Yes | K45: 1 | L45: Delivered | M45: Yes | N45: No | O45: 1
B46: 2 | C46: Rail | D46: Pakistan Railways Freight | E46: Bulk (25-35 t) | F46: Medium cost / medium | G46: Partial | K46: 2 | L46: In Transit | M46: No | N46: No | O46: 2
B47: 3 | C47: Road | D47: PakFreight Trucking | E47: Light (5-8 t) | F47: High cost / fast | G47: No | K47: 3 | L47: Delayed | M47: No | N47: Yes | O47: 3
B48: -1 | C48: Unknown | D48: Unknown | E48: Unknown | F48: Unknown | G48: Unknown | K48: -1 | L48: Unknown | M48: No | N48: Yes | O48: 99
B49: Both tables carry a row with key -1 called Unknown. It is not decoration: in T6 every lookup is a LEFT join, and a row whose mode nobody recognises must land somewhere visible rather than disappear. A fact row pointing at Unknown is a bug you can count; a fact row silently dropped is a bug you discover in a board meeting.
A51: BLOCK C · DIMDATE — 28 ROWS FOR FEBRUARY 2026, INCLUDING THE QUIET DAYS
B52: DateKey | C52: FullDate | D52: Year | E52: Quarter | F52: MonthNumber | G52: MonthName | I52: DayOfMonth | K52: DayNumber | L52: DayName | M52: IsWeekend | N52: IsHoliday | O52: Shipments that day | P52: In fact table?
B53: =YEAR(C53)*10000+MONTH(C53)*100+DAY(C53) | C53: 46054 | D53: 2026 | E53: Q1 | F53: 2 | G53: February | I53: 1 | K53: 1 | L53: Sunday | M53: Yes | N53: No | O53: =COUNTIF(Shipments_Unified!$B$5:$B$38,C53) | P53: =IF(O53>0,"yes","— quiet day")
B54: =YEAR(C54)*10000+MONTH(C54)*100+DAY(C54) | C54: 46055 | D54: 2026 | E54: Q1 | F54: 2 | G54: February | I54: 2 | K54: 2 | L54: Monday | M54: No | N54: No | O54: =COUNTIF(Shipments_Unified!$B$5:$B$38,C54) | P54: =IF(O54>0,"yes","— quiet day")
B55: =YEAR(C55)*10000+MONTH(C55)*100+DAY(C55) | C55: 46056 | D55: 2026 | E55: Q1 | F55: 2 | G55: February | I55: 3 | K55: 3 | L55: Tuesday | M55: No | N55: No | O55: =COUNTIF(Shipments_Unified!$B$5:$B$38,C55) | P55: =IF(O55>0,"yes","— quiet day")
B56: =YEAR(C56)*10000+MONTH(C56)*100+DAY(C56) | C56: 46057 | D56: 2026 | E56: Q1 | F56: 2 | G56: February | I56: 4 | K56: 4 | L56: Wednesday | M56: No | N56: No | O56: =COUNTIF(Shipments_Unified!$B$5:$B$38,C56) | P56: =IF(O56>0,"yes","— quiet day")
B57: =YEAR(C57)*10000+MONTH(C57)*100+DAY(C57) | C57: 46058 | D57: 2026 | E57: Q1 | F57: 2 | G57: February | I57: 5 | K57: 5 | L57: Thursday | M57: No | N57: Yes | O57: =COUNTIF(Shipments_Unified!$B$5:$B$38,C57) | P57: =IF(O57>0,"yes","— quiet day")
B58: =YEAR(C58)*10000+MONTH(C58)*100+DAY(C58) | C58: 46059 | D58: 2026 | E58: Q1 | F58: 2 | G58: February | I58: 6 | K58: 6 | L58: Friday | M58: No | N58: No | O58: =COUNTIF(Shipments_Unified!$B$5:$B$38,C58) | P58: =IF(O58>0,"yes","— quiet day")
B59: =YEAR(C59)*10000+MONTH(C59)*100+DAY(C59) | C59: 46060 | D59: 2026 | E59: Q1 | F59: 2 | G59: February | I59: 7 | K59: 7 | L59: Saturday | M59: Yes | N59: No | O59: =COUNTIF(Shipments_Unified!$B$5:$B$38,C59) | P59: =IF(O59>0,"yes","— quiet day")
B60: =YEAR(C60)*10000+MONTH(C60)*100+DAY(C60) | C60: 46061 | D60: 2026 | E60: Q1 | F60: 2 | G60: February | I60: 8 | K60: 1 | L60: Sunday | M60: Yes | N60: No | O60: =COUNTIF(Shipments_Unified!$B$5:$B$38,C60) | P60: =IF(O60>0,"yes","— quiet day")
B61: =YEAR(C61)*10000+MONTH(C61)*100+DAY(C61) | C61: 46062 | D61: 2026 | E61: Q1 | F61: 2 | G61: February | I61: 9 | K61: 2 | L61: Monday | M61: No | N61: No | O61: =COUNTIF(Shipments_Unified!$B$5:$B$38,C61) | P61: =IF(O61>0,"yes","— quiet day")
B62: =YEAR(C62)*10000+MONTH(C62)*100+DAY(C62) | C62: 46063 | D62: 2026 | E62: Q1 | F62: 2 | G62: February | I62: 10 | K62: 3 | L62: Tuesday | M62: No | N62: No | O62: =COUNTIF(Shipments_Unified!$B$5:$B$38,C62) | P62: =IF(O62>0,"yes","— quiet day")
B63: =YEAR(C63)*10000+MONTH(C63)*100+DAY(C63) | C63: 46064 | D63: 2026 | E63: Q1 | F63: 2 | G63: February | I63: 11 | K63: 4 | L63: Wednesday | M63: No | N63: No | O63: =COUNTIF(Shipments_Unified!$B$5:$B$38,C63) | P63: =IF(O63>0,"yes","— quiet day")
B64: =YEAR(C64)*10000+MONTH(C64)*100+DAY(C64) | C64: 46065 | D64: 2026 | E64: Q1 | F64: 2 | G64: February | I64: 12 | K64: 5 | L64: Thursday | M64: No | N64: No | O64: =COUNTIF(Shipments_Unified!$B$5:$B$38,C64) | P64: =IF(O64>0,"yes","— quiet day")
... B80: =YEAR(C80)*10000+MONTH(C80)*100+DAY(C80) | C80: 46081 | D80: 2026 | E80: Q1 | F80: 2 | G80: February | I80: 28 | K80: 7 | L80: Saturday | M80: Yes | N80: No | O80: =COUNTIF(Shipments_Unified!$B$5:$B$38,C80) | P80: =IF(O80>0,"yes","— quiet day")
C81: Rows in DimDate | D81: =COUNTA(C53:C80) | F81: Days with at least one shipment | I81: =COUNTIF(O53:O80,">0") | K81: Quiet days | M81: =COUNTIF(O53:O80,0)
A82: Expected: 28 rows, 12 days with shipments, 16 quiet days. THE question this answers: 'what was our average daily tonnage in February?' is 578,650 / 12 = 48,221 kg if you count only the days that appear in the fact table, and 578,650 / 28 = 20,666 kg against the real calendar. Both are arithmetically correct. Only one of them answers the question the CFO asked.
A84: ANSWER IN ONE LINE EACH
B85: DimRoute holds two city keys. Does that make DimCity a snowflake? One sentence. | I85: No. DimRoute stores the origin and destination keys as route attributes; without relationships from DimRoute to DimCity, the fact joins directly to DimCity in its origin/destination roles, so the model remains a star.
B87: Karachi → Lahore is served by both marine and rail. Should Mode be a column in DimRoute, or stay its own dimension? Why? | I87: Keep Mode separate: the same city pair can use several modes, so putting mode in DimRoute duplicates the route per mode and mixes two independent pieces of context.
B89: PakFreight adds a Karachi → Lahore service routed via Sukkur. Same two cities, different path. New DimRoute row or not? | I89: Under the current route grain (origin city + destination city), no: via-Sukkur is the same route key and the path is not represented. If path-specific analysis is required, extend the route grain with a path/service variant, then add a distinct row.
B91: Why does DimDate get 28 rows when the fact table only ever touches 12 of them? | I91: A complete calendar includes quiet dates, enabling continuous daily charts, correct calendar-day averages and time comparisons; the fact table only has rows on 12 dates.
A94: Marking, 20 marks: the conform-then-dedupe answer 3 · DimRoute 6 · DimMode and DimStatus with -1 rows 3 · DimDate 4 · the four questions 4.

Sheet T6 FactShipment
A1: T6 · Build FactShipment — Swap Every Text Column for an Integer Key
A2: Left of the gap: Shipments_Unified exactly as Week 2 left it. Right of the gap: the fact table. Row 6 is worked for you — copy it down to row 39. The rule you must not break: no descriptive text crosses the gap.
A3: Row 6 is worked for you — copy J6:S6 down to row 39. Until T4 and T5 are filled in, every key in row 6 reads -1. That is not an error: it is the Unknown row doing its job, because IFERROR sends an unmatched lookup to key -1 instead of losing the fact row. Watch them turn into real keys as you complete the dimensions.
A4: SOURCE · grey, do not edit | J4: FACTSHIPMENT · six keys + one degenerate + three measures | U4: EXCEL-ONLY SCRATCH
A5: ShipmentID | B5: ShipDate | C5: Origin | D5: Destination | E5: Source | F5: Status | G5: WeightKG | H5: CostPKR | J5: DateKey | K5: OriginCityKey | L5: DestCityKey | M5: RouteKey | N5: ModeKey | O5: StatusKey | P5: ShipmentID | Q5: WeightKG | R5: FreightCostPKR | S5: Count | U5: OriginProvince | V5: ModeName
A6: MR-1001 | B6: 46054 | C6: Karachi Port | D6: Lahore Dry Port | E6: Marine | F6: Delivered | G6: 18000 | H6: 142000 | J6: =YEAR(B6)*10000+MONTH(B6)*100+DAY(B6) | K6: =IFERROR(INDEX('T4 DimCity'!$I$6:$I$20,MATCH(INDEX('T4 DimCity'!$C$6:$C$28,MATCH(C6,'T4 DimCity'!$B$6:$B$28,0)),'T4 DimCity'!$J$6:$J$20,0)),-1) | L6: =IFERROR(INDEX('T4 DimCity'!$I$6:$I$20,MATCH(INDEX('T4 DimCity'!$C$6:$C$28,MATCH(D6,'T4 DimCity'!$B$6:$B$28,0)),'T4 DimCity'!$J$6:$J$20,0)),-1) | M6: =IFERROR(INDEX('T5 Other Dimensions'!$B$10:$B$30,MATCH(INDEX('T4 DimCity'!$C$6:$C$28,MATCH(C6,'T4 DimCity'!$B$6:$B$28,0))&" -> "&INDEX('T4 DimCity'!$C$6:$C$28,MATCH(D6,'T4 DimCity'!$B$6:$B$28,0)),'T5 Other Dimensions'!$E$10:$E$30,0)),-1) | N6: =IFERROR(INDEX('T5 Other Dimensions'!$B$45:$B$48,MATCH(E6,'T5 Other Dimensions'!$C$45:$C$48,0)),-1) | O6: =IFERROR(INDEX('T5 Other Dimensions'!$K$45:$K$48,MATCH(F6,'T5 Other Dimensions'!$L$45:$L$48,0)),-1) | P6: =A6 | Q6: =G6 | R6: =H6 | S6: 1 | U6: =IFERROR(INDEX('T4 DimCity'!$K$6:$K$20,MATCH(K6,'T4 DimCity'!$I$6:$I$20,0)),"?") | V6: =IFERROR(INDEX('T5 Other Dimensions'!$C$45:$C$48,MATCH(N6,'T5 Other Dimensions'!$B$45:$B$48,0)),"?")
A7: MR-1002 | B7: 46055 | C7: Port Qasim | D7: Faisalabad Dry Port | E7: Marine | F7: Delivered | G7: 22500 | H7: 171000 | J7: =YEAR(B7)*10000+MONTH(B7)*100+DAY(B7) | K7: =IFERROR(INDEX('T4 DimCity'!$I$6:$I$20,MATCH(INDEX('T4 DimCity'!$C$6:$C$28,MATCH(C7,'T4 DimCity'!$B$6:$B$28,0)),'T4 DimCity'!$J$6:$J$20,0)),-1) | L7: =IFERROR(INDEX('T4 DimCity'!$I$6:$I$20,MATCH(INDEX('T4 DimCity'!$C$6:$C$28,MATCH(D7,'T4 DimCity'!$B$6:$B$28,0)),'T4 DimCity'!$J$6:$J$20,0)),-1) | M7: =IFERROR(INDEX('T5 Other Dimensions'!$B$10:$B$30,MATCH(INDEX('T4 DimCity'!$C$6:$C$28,MATCH(C7,'T4 DimCity'!$B$6:$B$28,0))&" -> "&INDEX('T4 DimCity'!$C$6:$C$28,MATCH(D7,'T4 DimCity'!$B$6:$B$28,0)),'T5 Other Dimensions'!$E$10:$E$30,0)),-1) | N7: =IFERROR(INDEX('T5 Other Dimensions'!$B$45:$B$48,MATCH(E7,'T5 Other Dimensions'!$C$45:$C$48,0)),-1) | O7: =IFERROR(INDEX('T5 Other Dimensions'!$K$45:$K$48,MATCH(F7,'T5 Other Dimensions'!$L$45:$L$48,0)),-1) | P7: =A7 | Q7: =G7 | R7: =H7 | S7: 1 | U7: =IFERROR(INDEX('T4 DimCity'!$K$6:$K$20,MATCH(K7,'T4 DimCity'!$I$6:$I$20,0)),"?") | V7: =IFERROR(INDEX('T5 Other Dimensions'!$C$45:$C$48,MATCH(N7,'T5 Other Dimensions'!$B$45:$B$48,0)),"?")
A8: MR-1003 | B8: 46056 | C8: Karachi Port | D8: Lahore Dry Port | E8: Marine | F8: In Transit | G8: 15000 | H8: 119000 | J8: =YEAR(B8)*10000+MONTH(B8)*100+DAY(B8) | K8: =IFERROR(INDEX('T4 DimCity'!$I$6:$I$20,MATCH(INDEX('T4 DimCity'!$C$6:$C$28,MATCH(C8,'T4 DimCity'!$B$6:$B$28,0)),'T4 DimCity'!$J$6:$J$20,0)),-1) | L8: =IFERROR(INDEX('T4 DimCity'!$I$6:$I$20,MATCH(INDEX('T4 DimCity'!$C$6:$C$28,MATCH(D8,'T4 DimCity'!$B$6:$B$28,0)),'T4 DimCity'!$J$6:$J$20,0)),-1) | M8: =IFERROR(INDEX('T5 Other Dimensions'!$B$10:$B$30,MATCH(INDEX('T4 DimCity'!$C$6:$C$28,MATCH(C8,'T4 DimCity'!$B$6:$B$28,0))&" -> "&INDEX('T4 DimCity'!$C$6:$C$28,MATCH(D8,'T4 DimCity'!$B$6:$B$28,0)),'T5 Other Dimensions'!$E$10:$E$30,0)),-1) | N8: =IFERROR(INDEX('T5 Other Dimensions'!$B$45:$B$48,MATCH(E8,'T5 Other Dimensions'!$C$45:$C$48,0)),-1) | O8: =IFERROR(INDEX('T5 Other Dimensions'!$K$45:$K$48,MATCH(F8,'T5 Other Dimensions'!$L$45:$L$48,0)),-1) | P8: =A8 | Q8: =G8 | R8: =H8 | S8: 1 | U8: =IFERROR(INDEX('T4 DimCity'!$K$6:$K$20,MATCH(K8,'T4 DimCity'!$I$6:$I$20,0)),"?") | V8: =IFERROR(INDEX('T5 Other Dimensions'!$C$45:$C$48,MATCH(N8,'T5 Other Dimensions'!$B$45:$B$48,0)),"?")
A9: MR-1004 | B9: 46057 | C9: Gwadar Port | D9: Quetta | E9: Marine | F9: Delivered | G9: 20000 | H9: 188000 | J9: =YEAR(B9)*10000+MONTH(B9)*100+DAY(B9) | K9: =IFERROR(INDEX('T4 DimCity'!$I$6:$I$20,MATCH(INDEX('T4 DimCity'!$C$6:$C$28,MATCH(C9,'T4 DimCity'!$B$6:$B$28,0)),'T4 DimCity'!$J$6:$J$20,0)),-1) | L9: =IFERROR(INDEX('T4 DimCity'!$I$6:$I$20,MATCH(INDEX('T4 DimCity'!$C$6:$C$28,MATCH(D9,'T4 DimCity'!$B$6:$B$28,0)),'T4 DimCity'!$J$6:$J$20,0)),-1) | M9: =IFERROR(INDEX('T5 Other Dimensions'!$B$10:$B$30,MATCH(INDEX('T4 DimCity'!$C$6:$C$28,MATCH(C9,'T4 DimCity'!$B$6:$B$28,0))&" -> "&INDEX('T4 DimCity'!$C$6:$C$28,MATCH(D9,'T4 DimCity'!$B$6:$B$28,0)),'T5 Other Dimensions'!$E$10:$E$30,0)),-1) | N9: =IFERROR(INDEX('T5 Other Dimensions'!$B$45:$B$48,MATCH(E9,'T5 Other Dimensions'!$C$45:$C$48,0)),-1) | O9: =IFERROR(INDEX('T5 Other Dimensions'!$K$45:$K$48,MATCH(F9,'T5 Other Dimensions'!$L$45:$L$48,0)),-1) | P9: =A9 | Q9: =G9 | R9: =H9 | S9: 1 | U9: =IFERROR(INDEX('T4 DimCity'!$K$6:$K$20,MATCH(K9,'T4 DimCity'!$I$6:$I$20,0)),"?") | V9: =IFERROR(INDEX('T5 Other Dimensions'!$C$45:$C$48,MATCH(N9,'T5 Other Dimensions'!$B$45:$B$48,0)),"?")
A10: MR-1005 | B10: 46058 | C10: Port Qasim | D10: Multan | E10: Marine | F10: Delivered | G10: 16500 | H10: 128000 | J10: =YEAR(B10)*10000+MONTH(B10)*100+DAY(B10) | K10: =IFERROR(INDEX('T4 DimCity'!$I$6:$I$20,MATCH(INDEX('T4 DimCity'!$C$6:$C$28,MATCH(C10,'T4 DimCity'!$B$6:$B$28,0)),'T4 DimCity'!$J$6:$J$20,0)),-1) | L10: =IFERROR(INDEX('T4 DimCity'!$I$6:$I$20,MATCH(INDEX('T4 DimCity'!$C$6:$C$28,MATCH(D10,'T4 DimCity'!$B$6:$B$28,0)),'T4 DimCity'!$J$6:$J$20,0)),-1) | M10: =IFERROR(INDEX('T5 Other Dimensions'!$B$10:$B$30,MATCH(INDEX('T4 DimCity'!$C$6:$C$28,MATCH(C10,'T4 DimCity'!$B$6:$B$28,0))&" -> "&INDEX('T4 DimCity'!$C$6:$C$28,MATCH(D10,'T4 DimCity'!$B$6:$B$28,0)),'T5 Other Dimensions'!$E$10:$E$30,0)),-1) | N10: =IFERROR(INDEX('T5 Other Dimensions'!$B$45:$B$48,MATCH(E10,'T5 Other Dimensions'!$C$45:$C$48,0)),-1) | O10: =IFERROR(INDEX('T5 Other Dimensions'!$K$45:$K$48,MATCH(F10,'T5 Other Dimensions'!$L$45:$L$48,0)),-1) | P10: =A10 | Q10: =G10 | R10: =H10 | S10: 1 | U10: =IFERROR(INDEX('T4 DimCity'!$K$6:$K$20,MATCH(K10,'T4 DimCity'!$I$6:$I$20,0)),"?") | V10: =IFERROR(INDEX('T5 Other Dimensions'!$C$45:$C$48,MATCH(N10,'T5 Other Dimensions'!$B$45:$B$48,0)),"?")
A11: MR-1006 | B11: 46059 | C11: Karachi Port | D11: Sialkot Dry Port | E11: Marine | F11: Delayed | G11: 19000 | H11: 154000 | J11: =YEAR(B11)*10000+MONTH(B11)*100+DAY(B11) | K11: =IFERROR(INDEX('T4 DimCity'!$I$6:$I$20,MATCH(INDEX('T4 DimCity'!$C$6:$C$28,MATCH(C11,'T4 DimCity'!$B$6:$B$28,0)),'T4 DimCity'!$J$6:$J$20,0)),-1) | L11: =IFERROR(INDEX('T4 DimCity'!$I$6:$I$20,MATCH(INDEX('T4 DimCity'!$C$6:$C$28,MATCH(D11,'T4 DimCity'!$B$6:$B$28,0)),'T4 DimCity'!$J$6:$J$20,0)),-1) | M11: =IFERROR(INDEX('T5 Other Dimensions'!$B$10:$B$30,MATCH(INDEX('T4 DimCity'!$C$6:$C$28,MATCH(C11,'T4 DimCity'!$B$6:$B$28,0))&" -> "&INDEX('T4 DimCity'!$C$6:$C$28,MATCH(D11,'T4 DimCity'!$B$6:$B$28,0)),'T5 Other Dimensions'!$E$10:$E$30,0)),-1) | N11: =IFERROR(INDEX('T5 Other Dimensions'!$B$45:$B$48,MATCH(E11,'T5 Other Dimensions'!$C$45:$C$48,0)),-1) | O11: =IFERROR(INDEX('T5 Other Dimensions'!$K$45:$K$48,MATCH(F11,'T5 Other Dimensions'!$L$45:$L$48,0)),-1) | P11: =A11 | Q11: =G11 | R11: =H11 | S11: 1 | U11: =IFERROR(INDEX('T4 DimCity'!$K$6:$K$20,MATCH(K11,'T4 DimCity'!$I$6:$I$20,0)),"?") | V11: =IFERROR(INDEX('T5 Other Dimensions'!$C$45:$C$48,MATCH(N11,'T5 Other Dimensions'!$B$45:$B$48,0)),"?")
A12: MR-1007 | B12: 46060 | C12: Port Qasim | D12: Lahore Dry Port | E12: Marine | F12: Delivered | G12: 14000 | H12: 109000 | J12: =YEAR(B12)*10000+MONTH(B12)*100+DAY(B12) | K12: =IFERROR(INDEX('T4 DimCity'!$I$6:$I$20,MATCH(INDEX('T4 DimCity'!$C$6:$C$28,MATCH(C12,'T4 DimCity'!$B$6:$B$28,0)),'T4 DimCity'!$J$6:$J$20,0)),-1) | L12: =IFERROR(INDEX('T4 DimCity'!$I$6:$I$20,MATCH(INDEX('T4 DimCity'!$C$6:$C$28,MATCH(D12,'T4 DimCity'!$B$6:$B$28,0)),'T4 DimCity'!$J$6:$J$20,0)),-1) | M12: =IFERROR(INDEX('T5 Other Dimensions'!$B$10:$B$30,MATCH(INDEX('T4 DimCity'!$C$6:$C$28,MATCH(C12,'T4 DimCity'!$B$6:$B$28,0))&" -> "&INDEX('T4 DimCity'!$C$6:$C$28,MATCH(D12,'T4 DimCity'!$B$6:$B$28,0)),'T5 Other Dimensions'!$E$10:$E$30,0)),-1) | N12: =IFERROR(INDEX('T5 Other Dimensions'!$B$45:$B$48,MATCH(E12,'T5 Other Dimensions'!$C$45:$C$48,0)),-1) | O12: =IFERROR(INDEX('T5 Other Dimensions'!$K$45:$K$48,MATCH(F12,'T5 Other Dimensions'!$L$45:$L$48,0)),-1) | P12: =A12 | Q12: =G12 | R12: =H12 | S12: 1 | U12: =IFERROR(INDEX('T4 DimCity'!$K$6:$K$20,MATCH(K12,'T4 DimCity'!$I$6:$I$20,0)),"?") | V12: =IFERROR(INDEX('T5 Other Dimensions'!$C$45:$C$48,MATCH(N12,'T5 Other Dimensions'!$B$45:$B$48,0)),"?")
A13: MR-1008 | B13: 46062 | C13: Karachi Port | D13: Peshawar | E13: Marine | F13: In Transit | G13: 21000 | H13: 197000 | J13: =YEAR(B13)*10000+MONTH(B13)*100+DAY(B13) | K13: =IFERROR(INDEX('T4 DimCity'!$I$6:$I$20,MATCH(INDEX('T4 DimCity'!$C$6:$C$28,MATCH(C13,'T4 DimCity'!$B$6:$B$28,0)),'T4 DimCity'!$J$6:$J$20,0)),-1) | L13: =IFERROR(INDEX('T4 DimCity'!$I$6:$I$20,MATCH(INDEX('T4 DimCity'!$C$6:$C$28,MATCH(D13,'T4 DimCity'!$B$6:$B$28,0)),'T4 DimCity'!$J$6:$J$20,0)),-1) | M13: =IFERROR(INDEX('T5 Other Dimensions'!$B$10:$B$30,MATCH(INDEX('T4 DimCity'!$C$6:$C$28,MATCH(C13,'T4 DimCity'!$B$6:$B$28,0))&" -> "&INDEX('T4 DimCity'!$C$6:$C$28,MATCH(D13,'T4 DimCity'!$B$6:$B$28,0)),'T5 Other Dimensions'!$E$10:$E$30,0)),-1) | N13: =IFERROR(INDEX('T5 Other Dimensions'!$B$45:$B$48,MATCH(E13,'T5 Other Dimensions'!$C$45:$C$48,0)),-1) | O13: =IFERROR(INDEX('T5 Other Dimensions'!$K$45:$K$48,MATCH(F13,'T5 Other Dimensions'!$L$45:$L$48,0)),-1) | P13: =A13 | Q13: =G13 | R13: =H13 | S13: 1 | U13: =IFERROR(INDEX('T4 DimCity'!$K$6:$K$20,MATCH(K13,'T4 DimCity'!$I$6:$I$20,0)),"?") | V13: =IFERROR(INDEX('T5 Other Dimensions'!$C$45:$C$48,MATCH(N13,'T5 Other Dimensions'!$B$45:$B$48,0)),"?")
A14: MR-1009 | B14: 46063 | C14: Gwadar Port | D14: Karachi Cantt | E14: Marine | F14: Delivered | G14: 17500 | H14: 98000 | J14: =YEAR(B14)*10000+MONTH(B14)*100+DAY(B14) | K14: =IFERROR(INDEX('T4 DimCity'!$I$6:$I$20,MATCH(INDEX('T4 DimCity'!$C$6:$C$28,MATCH(C14,'T4 DimCity'!$B$6:$B$28,0)),'T4 DimCity'!$J$6:$J$20,0)),-1) | L14: =IFERROR(INDEX('T4 DimCity'!$I$6:$I$20,MATCH(INDEX('T4 DimCity'!$C$6:$C$28,MATCH(D14,'T4 DimCity'!$B$6:$B$28,0)),'T4 DimCity'!$J$6:$J$20,0)),-1) | M14: =IFERROR(INDEX('T5 Other Dimensions'!$B$10:$B$30,MATCH(INDEX('T4 DimCity'!$C$6:$C$28,MATCH(C14,'T4 DimCity'!$B$6:$B$28,0))&" -> "&INDEX('T4 DimCity'!$C$6:$C$28,MATCH(D14,'T4 DimCity'!$B$6:$B$28,0)),'T5 Other Dimensions'!$E$10:$E$30,0)),-1) | N14: =IFERROR(INDEX('T5 Other Dimensions'!$B$45:$B$48,MATCH(E14,'T5 Other Dimensions'!$C$45:$C$48,0)),-1) | O14: =IFERROR(INDEX('T5 Other Dimensions'!$K$45:$K$48,MATCH(F14,'T5 Other Dimensions'!$L$45:$L$48,0)),-1) | P14: =A14 | Q14: =G14 | R14: =H14 | S14: 1 | U14: =IFERROR(INDEX('T4 DimCity'!$K$6:$K$20,MATCH(K14,'T4 DimCity'!$I$6:$I$20,0)),"?") | V14: =IFERROR(INDEX('T5 Other Dimensions'!$C$45:$C$48,MATCH(N14,'T5 Other Dimensions'!$B$45:$B$48,0)),"?")
A15: MR-1010 | B15: 46064 | C15: Port Qasim | D15: Islamabad Dry Port | E15: Marine | F15: Delivered | G15: 15500 | H15: 139000 | J15: =YEAR(B15)*10000+MONTH(B15)*100+DAY(B15) | K15: =IFERROR(INDEX('T4 DimCity'!$I$6:$I$20,MATCH(INDEX('T4 DimCity'!$C$6:$C$28,MATCH(C15,'T4 DimCity'!$B$6:$B$28,0)),'T4 DimCity'!$J$6:$J$20,0)),-1) | L15: =IFERROR(INDEX('T4 DimCity'!$I$6:$I$20,MATCH(INDEX('T4 DimCity'!$C$6:$C$28,MATCH(D15,'T4 DimCity'!$B$6:$B$28,0)),'T4 DimCity'!$J$6:$J$20,0)),-1) | M15: =IFERROR(INDEX('T5 Other Dimensions'!$B$10:$B$30,MATCH(INDEX('T4 DimCity'!$C$6:$C$28,MATCH(C15,'T4 DimCity'!$B$6:$B$28,0))&" -> "&INDEX('T4 DimCity'!$C$6:$C$28,MATCH(D15,'T4 DimCity'!$B$6:$B$28,0)),'T5 Other Dimensions'!$E$10:$E$30,0)),-1) | N15: =IFERROR(INDEX('T5 Other Dimensions'!$B$45:$B$48,MATCH(E15,'T5 Other Dimensions'!$C$45:$C$48,0)),-1) | O15: =IFERROR(INDEX('T5 Other Dimensions'!$K$45:$K$48,MATCH(F15,'T5 Other Dimensions'!$L$45:$L$48,0)),-1) | P15: =A15 | Q15: =G15 | R15: =H15 | S15: 1 | U15: =IFERROR(INDEX('T4 DimCity'!$K$6:$K$20,MATCH(K15,'T4 DimCity'!$I$6:$I$20,0)),"?") | V15: =IFERROR(INDEX('T5 Other Dimensions'!$C$45:$C$48,MATCH(N15,'T5 Other Dimensions'!$B$45:$B$48,0)),"?")
A16: MR-1011 | B16: 46065 | C16: Karachi Port | D16: Hyderabad | E16: Marine | F16: In Transit | G16: 13500 | H16: 61000 | J16: =YEAR(B16)*10000+MONTH(B16)*100+DAY(B16) | K16: =IFERROR(INDEX('T4 DimCity'!$I$6:$I$20,MATCH(INDEX('T4 DimCity'!$C$6:$C$28,MATCH(C16,'T4 DimCity'!$B$6:$B$28,0)),'T4 DimCity'!$J$6:$J$20,0)),-1) | L16: =IFERROR(INDEX('T4 DimCity'!$I$6:$I$20,MATCH(INDEX('T4 DimCity'!$C$6:$C$28,MATCH(D16,'T4 DimCity'!$B$6:$B$28,0)),'T4 DimCity'!$J$6:$J$20,0)),-1) | M16: =IFERROR(INDEX('T5 Other Dimensions'!$B$10:$B$30,MATCH(INDEX('T4 DimCity'!$C$6:$C$28,MATCH(C16,'T4 DimCity'!$B$6:$B$28,0))&" -> "&INDEX('T4 DimCity'!$C$6:$C$28,MATCH(D16,'T4 DimCity'!$B$6:$B$28,0)),'T5 Other Dimensions'!$E$10:$E$30,0)),-1) | N16: =IFERROR(INDEX('T5 Other Dimensions'!$B$45:$B$48,MATCH(E16,'T5 Other Dimensions'!$C$45:$C$48,0)),-1) | O16: =IFERROR(INDEX('T5 Other Dimensions'!$K$45:$K$48,MATCH(F16,'T5 Other Dimensions'!$L$45:$L$48,0)),-1) | P16: =A16 | Q16: =G16 | R16: =H16 | S16: 1 | U16: =IFERROR(INDEX('T4 DimCity'!$K$6:$K$20,MATCH(K16,'T4 DimCity'!$I$6:$I$20,0)),"?") | V16: =IFERROR(INDEX('T5 Other Dimensions'!$C$45:$C$48,MATCH(N16,'T5 Other Dimensions'!$B$45:$B$48,0)),"?")
A17: MR-1012 | B17: 46066 | C17: Port Qasim | D17: Lahore Dry Port | E17: Marine | F17: Delivered | G17: 14000 | H17: 112000 | J17: =YEAR(B17)*10000+MONTH(B17)*100+DAY(B17) | K17: =IFERROR(INDEX('T4 DimCity'!$I$6:$I$20,MATCH(INDEX('T4 DimCity'!$C$6:$C$28,MATCH(C17,'T4 DimCity'!$B$6:$B$28,0)),'T4 DimCity'!$J$6:$J$20,0)),-1) | L17: =IFERROR(INDEX('T4 DimCity'!$I$6:$I$20,MATCH(INDEX('T4 DimCity'!$C$6:$C$28,MATCH(D17,'T4 DimCity'!$B$6:$B$28,0)),'T4 DimCity'!$J$6:$J$20,0)),-1) | M17: =IFERROR(INDEX('T5 Other Dimensions'!$B$10:$B$30,MATCH(INDEX('T4 DimCity'!$C$6:$C$28,MATCH(C17,'T4 DimCity'!$B$6:$B$28,0))&" -> "&INDEX('T4 DimCity'!$C$6:$C$28,MATCH(D17,'T4 DimCity'!$B$6:$B$28,0)),'T5 Other Dimensions'!$E$10:$E$30,0)),-1) | N17: =IFERROR(INDEX('T5 Other Dimensions'!$B$45:$B$48,MATCH(E17,'T5 Other Dimensions'!$C$45:$C$48,0)),-1) | O17: =IFERROR(INDEX('T5 Other Dimensions'!$K$45:$K$48,MATCH(F17,'T5 Other Dimensions'!$L$45:$L$48,0)),-1) | P17: =A17 | Q17: =G17 | R17: =H17 | S17: 1 | U17: =IFERROR(INDEX('T4 DimCity'!$K$6:$K$20,MATCH(K17,'T4 DimCity'!$I$6:$I$20,0)),"?") | V17: =IFERROR(INDEX('T5 Other Dimensions'!$C$45:$C$48,MATCH(N17,'T5 Other Dimensions'!$B$45:$B$48,0)),"?")
... A39: RD-512 | B39: 46066 | C39: Rawalpindi | D39: Abbottabad | E39: Road | F39: Delivered | G39: 5800 | H39: 45000 | J39: =YEAR(B39)*10000+MONTH(B39)*100+DAY(B39) | K39: =IFERROR(INDEX('T4 DimCity'!$I$6:$I$20,MATCH(INDEX('T4 DimCity'!$C$6:$C$28,MATCH(C39,'T4 DimCity'!$B$6:$B$28,0)),'T4 DimCity'!$J$6:$J$20,0)),-1) | L39: =IFERROR(INDEX('T4 DimCity'!$I$6:$I$20,MATCH(INDEX('T4 DimCity'!$C$6:$C$28,MATCH(D39,'T4 DimCity'!$B$6:$B$28,0)),'T4 DimCity'!$J$6:$J$20,0)),-1) | M39: =IFERROR(INDEX('T5 Other Dimensions'!$B$10:$B$30,MATCH(INDEX('T4 DimCity'!$C$6:$C$28,MATCH(C39,'T4 DimCity'!$B$6:$B$28,0))&" -> "&INDEX('T4 DimCity'!$C$6:$C$28,MATCH(D39,'T4 DimCity'!$B$6:$B$28,0)),'T5 Other Dimensions'!$E$10:$E$30,0)),-1) | N39: =IFERROR(INDEX('T5 Other Dimensions'!$B$45:$B$48,MATCH(E39,'T5 Other Dimensions'!$C$45:$C$48,0)),-1) | O39: =IFERROR(INDEX('T5 Other Dimensions'!$K$45:$K$48,MATCH(F39,'T5 Other Dimensions'!$L$45:$L$48,0)),-1) | P39: =A39 | Q39: =G39 | R39: =H39 | S39: 1 | U39: =IFERROR(INDEX('T4 DimCity'!$K$6:$K$20,MATCH(K39,'T4 DimCity'!$I$6:$I$20,0)),"?") | V39: =IFERROR(INDEX('T5 Other Dimensions'!$C$45:$C$48,MATCH(N39,'T5 Other Dimensions'!$B$45:$B$48,0)),"?")
P40: TOTAL | Q40: =SUM(Q6:Q39) | R40: =SUM(R6:R39) | S40: =SUM(S6:S39)
A42: Columns U and V are a scratch pad, NOT part of the fact table. Excel has no relationships, so T7 needs the province and the mode name as text to build a matrix with SUMIFS. In Power BI the relationship does this for you and these two columns must not exist in your .pbix — if they do, you have put descriptive text back into a fact table and undone the whole exercise.
A44: THE THREE QUESTIONS THIS TASK IS REALLY ASKING
A45: Every lookup above is wrapped in IFERROR(…, -1) instead of being left to fail. Name what that buys you and what it costs you. | J45: IFERROR(...,-1) preserves every leg and makes missing context visible under the Unknown key; it can hide a bad mapping, so monitor Unknown counts and investigate them.
A47: Columns C to F still hold the text. Why do they not cross the gap into the fact table? | J47: Those fields describe the shipment. Store each description once in its dimension and keep only integer foreign keys plus the degenerate ShipmentID and numeric measures in the fact.
A49: ShipmentID is in the fact table but joins to nothing. Defend keeping it. | J49: ShipmentID is the degenerate dimension: it preserves the source transaction reference for drill-through, auditing and traceability, even without its own descriptive dimension.
A52: Marking, 15 marks: six key columns correct 9 · measures and degenerate key 3 · the three questions 3. A hard-typed key column instead of a lookup scores zero for that column — the point is the join, not the digit.

Sheet T7 Reconcile
A1: T7 · Reconcile — Thirteen Checks, All Thirteen Must Pass
A2: The reshaping must not change a single kilogram. Reconciliation is not a formality: it is the last moment at which you can still find the mistake cheaply.
A4: # | B4: Check | C4: Expected | D4: Your result | E4: Pass? | F4: If it does not match, look here first
A5: 1 | B5: Row count of FactShipment | C5: 34 | D5: =COUNT('T6 FactShipment'!$J$6:$J$39) | E5: =IF(D5=C5,"✔ pass","✘ fix") | F5: You dropped rows in a lookup, or you duplicated one to fit a dimension. A changed row count means the grain moved.
A6: 2 | B6: Grand total, WeightKG | C6: 578650 | D6: =SUM('T6 FactShipment'!$Q$6:$Q$39) | E6: =IF(D6=C6,"✔ pass","✘ fix") | F6: Rail is still in tonnes (a factor of 1,000 missing), or the rd-505 duplicate came back, or the Road TOTAL row survived staging.
A7: 3 | B7: Grand total, FreightCostPKR | C7: 4808000 | D7: =SUM('T6 FactShipment'!$R$6:$R$39) | E7: =IF(D7=C7,"✔ pass","✘ fix") | F7: Same causes as the weight check. Costs are additive currency — there is no rounding excuse.
A8: 4 | B8: Shipment legs (SUM of Count) | C8: 34 | D8: =SUM('T6 FactShipment'!$S$6:$S$39) | E8: =IF(D8=C8,"✔ pass","✘ fix") | F8: A measure problem, not a data problem — check that ShipmentCount is 1 on every row, including the last one.
A9: 5 | B9: Distinct ShipmentID values | C9: 34 | D9: =SUMPRODUCT(('T6 FactShipment'!$P$6:$P$39<>"")/COUNTIF('T6 FactShipment'!$P$6:$P$39,'T6 FactShipment'!$P$6:$P$39&"")) | E9: =IF(D9=C9,"✔ pass","✘ fix") | F9: Equal to the leg count here because no consignment was split. The day they differ, the grain sentence has to say which one a row is.
A10: 6 | B10: Rows in DimCity (excluding Unknown) | C10: 14 | D10: =COUNTIF('T4 DimCity'!$I$6:$I$20,">0") | E10: =IF(D10=C10,"✔ pass","✘ fix") | F10: Your conforming map is incomplete — you still have 23, or some number in between.
A11: 7 | B11: Rows in DimRoute (excluding Unknown) | C11: 20 | D11: =COUNTIF('T5 Other Dimensions'!$B$10:$B$30,">0") | E11: =IF(D11=C11,"✔ pass","✘ fix") | F11: 30 means you deduplicated the raw strings instead of the conformed city keys. Go back to T5 Block A.
A12: 8 | B12: Rows in DimDate | C12: 28 | D12: =COUNTA('T5 Other Dimensions'!$C$53:$C$80) | E12: =IF(D12=C12,"✔ pass","✘ fix") | F12: 12 means you generated only the dates that appear in the fact table. A date dimension with holes breaks every time-intelligence function.
A13: 9 | B13: WeightKG for Sindh / Marine | C13: 169000 | D13: =SUMIFS('T6 FactShipment'!$Q$6:$Q$39,'T6 FactShipment'!$U$6:$U$39,"Sindh",'T6 FactShipment'!$V$6:$V$39,"Marine") | E13: =IF(D13=C13,"✔ pass","✘ fix") | F13: If you got 206,500 you mapped Gwadar Port to Karachi. Gwadar is in Balochistan, and it is the one conforming decision students get wrong most often.
A14: 10 | B14: WeightKG for Punjab / Road | C14: 44100 | D14: =SUMIFS('T6 FactShipment'!$Q$6:$Q$39,'T6 FactShipment'!$U$6:$U$39,"Punjab",'T6 FactShipment'!$V$6:$V$39,"Road") | E14: =IF(D14=C14,"✔ pass","✘ fix") | F14: Check that Lahore, Faisalabad, Multan, Sialkot, Gujranwala and Rawalpindi all map to Punjab — and that Islamabad does NOT.
A15: 11 | B15: WeightKG for Sindh, all modes | C15: 484350 | D15: =SUMIFS('T6 FactShipment'!$Q$6:$Q$39,'T6 FactShipment'!$U$6:$U$39,"Sindh") | E15: =IF(D15=C15,"✔ pass","✘ fix") | F15: 83.7% of everything PakFreight moved. If it is lower, some Karachi alias is still its own city.
A16: 12 | B16: Fact rows pointing at an Unknown key (-1) | C16: 0 | D16: =COUNTIF('T6 FactShipment'!$K$6:$K$39,-1)+COUNTIF('T6 FactShipment'!$L$6:$L$39,-1)+COUNTIF('T6 FactShipment'!$M$6:$M$39,-1)+COUNTIF('T6 FactShipment'!$N$6:$N$39,-1)+COUNTIF('T6 FactShipment'!$O$6:$O$39,-1) | E16: =IF(D16=C16,"✔ pass","✘ fix") | F16: A lookup failed and IFERROR caught it. Which column, and which row? The -1 row exists so this is a number you can read, not a row you lost.
A17: 13 | B17: Cost per KG, grand total | C17: 8.31 | D17: =SUM('T6 FactShipment'!$R$6:$R$39)/SUM('T6 FactShipment'!$Q$6:$Q$39) | E17: =IF(ABS(D17-C17)<=0.005,"✔ pass","✘ fix") | F17: 8.06 means you averaged a ratio instead of dividing two sums. See T3 — this is the same 3% error, now wearing a dashboard.
B19: CHECKS PASSING | C19: =COUNTIF(E5:E17,"✔*")&" / 13" | D19: =IF(COUNTIF(E5:E17,"✔*")=13,"✔ SUBMIT","✘ NOT YET") | F19: Submitting with a single red cell loses all 8 marks for this task. Thirteen out of thirteen, or it is not done.
A21: THE DELIVERABLE MATRIX · TONNAGE BY ORIGIN PROVINCE AND MODE
A22: Build this in Power BI too: Province on rows, Mode on columns, Total Weight KG in values. The grand total must read 578,650 kg exactly.
B23: Origin province | C23: Marine | D23: Rail | E23: Road | F23: Total
B24: Sindh | C24: =SUMIFS('T6 FactShipment'!$Q$6:$Q$39,'T6 FactShipment'!$U$6:$U$39,$B24,'T6 FactShipment'!$V$6:$V$39,"Marine") | D24: =SUMIFS('T6 FactShipment'!$Q$6:$Q$39,'T6 FactShipment'!$U$6:$U$39,$B24,'T6 FactShipment'!$V$6:$V$39,"Rail") | E24: =SUMIFS('T6 FactShipment'!$Q$6:$Q$39,'T6 FactShipment'!$U$6:$U$39,$B24,'T6 FactShipment'!$V$6:$V$39,"Road") | F24: =SUM(C24:E24)
B25: Punjab | C25: =SUMIFS('T6 FactShipment'!$Q$6:$Q$39,'T6 FactShipment'!$U$6:$U$39,$B25,'T6 FactShipment'!$V$6:$V$39,"Marine") | D25: =SUMIFS('T6 FactShipment'!$Q$6:$Q$39,'T6 FactShipment'!$U$6:$U$39,$B25,'T6 FactShipment'!$V$6:$V$39,"Rail") | E25: =SUMIFS('T6 FactShipment'!$Q$6:$Q$39,'T6 FactShipment'!$U$6:$U$39,$B25,'T6 FactShipment'!$V$6:$V$39,"Road") | F25: =SUM(C25:E25)
B26: Balochistan | C26: =SUMIFS('T6 FactShipment'!$Q$6:$Q$39,'T6 FactShipment'!$U$6:$U$39,$B26,'T6 FactShipment'!$V$6:$V$39,"Marine") | D26: =SUMIFS('T6 FactShipment'!$Q$6:$Q$39,'T6 FactShipment'!$U$6:$U$39,$B26,'T6 FactShipment'!$V$6:$V$39,"Rail") | E26: =SUMIFS('T6 FactShipment'!$Q$6:$Q$39,'T6 FactShipment'!$U$6:$U$39,$B26,'T6 FactShipment'!$V$6:$V$39,"Road") | F26: =SUM(C26:E26)
B27: Khyber Pakhtunkhwa | C27: =SUMIFS('T6 FactShipment'!$Q$6:$Q$39,'T6 FactShipment'!$U$6:$U$39,$B27,'T6 FactShipment'!$V$6:$V$39,"Marine") | D27: =SUMIFS('T6 FactShipment'!$Q$6:$Q$39,'T6 FactShipment'!$U$6:$U$39,$B27,'T6 FactShipment'!$V$6:$V$39,"Rail") | E27: =SUMIFS('T6 FactShipment'!$Q$6:$Q$39,'T6 FactShipment'!$U$6:$U$39,$B27,'T6 FactShipment'!$V$6:$V$39,"Road") | F27: =SUM(C27:E27)
B28: Islamabad ICT | C28: =SUMIFS('T6 FactShipment'!$Q$6:$Q$39,'T6 FactShipment'!$U$6:$U$39,$B28,'T6 FactShipment'!$V$6:$V$39,"Marine") | D28: =SUMIFS('T6 FactShipment'!$Q$6:$Q$39,'T6 FactShipment'!$U$6:$U$39,$B28,'T6 FactShipment'!$V$6:$V$39,"Rail") | E28: =SUMIFS('T6 FactShipment'!$Q$6:$Q$39,'T6 FactShipment'!$U$6:$U$39,$B28,'T6 FactShipment'!$V$6:$V$39,"Road") | F28: =SUM(C28:E28)
B29: Grand total | C29: =SUM(C24:C28) | D29: =SUM(D24:D28) | E29: =SUM(E24:E28) | F29: =SUM(F24:F28)
B30: Reconciles to 578,650? | F30: =IF(F29=578650,"✔ pass","✘ fix")
A31: Read the Khyber Pakhtunkhwa row: zero. PakFreight moved 61,900 kg INTO Peshawar and Abbottabad in February and nothing out of them, and this matrix is built on OriginCityKey. The number is correct, and the conclusion a reader draws from it — 'KP is not part of our network' — is false. A role-playing dimension is exactly this: the same DimCity answers two different questions, and the active relationship silently decides which one you asked. Rebuild the matrix on DestCityKey and KP reads 61,900 kg. In Power BI that is the USERELATIONSHIP bonus on slide 47.
A33: THE LAST QUESTION · WRITE IT BEFORE YOU SUBMIT
A34: Every one of the thirteen checks above passes and your matrix totals 578,650 kg. In two or three lines: name one thing that could still be wrong with this model that no check on this sheet would ever catch. | C34: A model can pass every arithmetic check and still encode the wrong business meaning—for example, an incorrect corridor/distance-band rule or an agreed city/facility merge that misrepresents how operations make decisions. Reconciliation proves totals and keys, not that every editorial definition matches business reality.
A38: Marking, 8 marks: thirteen checks passing 5 (all or nothing) · the matrix 1 · the last question 2.
